tp/__init__.py
tp/client.py
tp/errors.py
tp/models.py
tp_sdk-0.2.0.dist-info/METADATA
tp_sdk-0.2.0.dist-info/WHEEL
tp_sdk-0.2.0.dist-info/licenses/LICENSE
tp_sdk-0.2.0.dist-info/RECORD
