Metadata-Version: 2.4
Name: tp-sdk
Version: 0.2.0
Summary: Python SDK for TeaserPaste API - Simple, Typed, and Fun.
Author-email: TeaserPaste <contact@teaserverse.online>
License: MIT License
License-File: LICENSE
Classifier: Operating System :: OS Independent
Classifier: Programming Language :: Python :: 3
Requires-Python: >=3.9
Requires-Dist: httpx>=0.27.0
Requires-Dist: pydantic>=2.0.0
